Metadata-Version: 2.1
Name: dynamodblock
Version: 1.0.5
Summary: DynamoDB Lock for AWS Lambdas is a pure Python lib that implements a distributed locking mechanism using DynamoDB. It's designed for scenarios where multiple concurrent Lambda executions need to ensure that certain tasks are performed exclusively by a single instance. Supports configurable TTL, retry logic with backoff, customizable timeouts and timezone.
Home-page: https://github.com/rabuchaim/dynamodblock
Author: Ricardo Abuchaim
Author-email: ricardoabuchaim@gmail.com
Maintainer: Ricardo Abuchaim
Maintainer-email: ricardoabuchaim@gmail.com
License: MIT
Project-URL: Issue Tracker, https://github.com/rabuchaim/dynamodblock/issues
Project-URL: Source code, https://github.com/rabuchaim/dynamodblock
Keywords: aws,lambda,dynamodb,lock
Classifier: Development Status :: 5 - Production/Stable
Classifier: Topic :: Security
Classifier: Topic :: Internet
Classifier: Topic :: Internet :: Finger
Classifier: Topic :: Scientific/Engineering
Classifier: Topic :: System :: Monitoring
Classifier: Topic :: System :: Networking
Classifier: Topic :: System :: Systems Administration
Classifier: Topic :: Software Development :: Libraries
Classifier: Topic :: Software Development :: Libraries :: Python Modules
Classifier: Topic :: Software Development :: Localization
Classifier: Topic :: Utilities
Classifier: Intended Audience :: Developers
Classifier: Intended Audience :: Information Technology
Classifier: Intended Audience :: System Administrators
Classifier: Operating System :: MacOS
Classifier: Operating System :: Microsoft :: Windows :: Windows 10
Classifier: Operating System :: Microsoft :: Windows :: Windows 11
Classifier: Operating System :: Unix
Classifier: Operating System :: POSIX
Classifier: Operating System :: POSIX :: Linux
Classifier: Operating System :: POSIX :: BSD
Classifier: Operating System :: POSIX :: BSD :: FreeBSD
Classifier: Programming Language :: Python
Classifier: Programming Language :: Python :: 3.10
Classifier: Programming Language :: Python :: 3.11
Classifier: Programming Language :: Python :: 3.12
Classifier: Programming Language :: Python :: 3.13
Classifier: Programming Language :: Python :: Implementation :: PyPy
Classifier: License :: OSI Approved :: MIT License
Requires-Python: >=3.10
License-File: LICENSE
